LICENSE
MANIFEST.in
README.md
setup.py
humblebee/__init__.py
humblebee/bing.py
humblebee/cfg.py
humblebee/cli.py
humblebee/dbguy.py
humblebee/default.cfg
humblebee/dirscanner.py
humblebee/entrypoint.py
humblebee/importer.py
humblebee/logger.py
humblebee/mediainfo.py
humblebee/parser.py
humblebee/quality.py
humblebee/renaming.py
humblebee/schema.sql
humblebee/texceptions.py
humblebee/tvdbwrapper.py
humblebee/tvregexes.py
humblebee/unrarman.py
humblebee/util.py
humblebee/virtualfs.py
humblebee.egg-info/PKG-INFO
humblebee.egg-info/SOURCES.txt
humblebee.egg-info/dependency_links.txt
humblebee.egg-info/entry_points.txt
humblebee.egg-info/requires.txt
humblebee.egg-info/top_level.txt