Metadata-Version: 1.0
Name: humblebee
Version: 1.101
Summary: A scraper for TV shows.
Home-page: https://github.com/steinitzu/humblebee
Author: Steinthor Palsson
Author-email: steinitzu@gmail.com
License: MIT
Platform: UNKNOWN
